vcfproj/__init__.py
vcfproj/vcfproj.py
vcfproj-0.0.3.dist-info/LICENSE
vcfproj-0.0.3.dist-info/METADATA
vcfproj-0.0.3.dist-info/WHEEL
vcfproj-0.0.3.dist-info/top_level.txt
vcfproj-0.0.3.dist-info/RECORD
