Metadata-Version: 2.1
Name: vcfproj
Version: 0.0.3
Summary: Project vcf level coordinates from chromosomes to transcript
Home-page: https://github.com/hiraksarkar/vcfproj
Author: Hirak Sarkar
Author-email: hsarkar@umd.edu
License: UNKNOWN
Platform: UNKNOWN
Classifier: Programming Language :: Python :: 3
Classifier: License :: OSI Approved :: MIT License
Classifier: Operating System :: OS Independent
Requires-Dist: pandas
Requires-Dist: numpy
Requires-Dist: ncls
